documentdb/__init__.py
documentdb-0.0.5.dist-info/METADATA
documentdb-0.0.5.dist-info/WHEEL
documentdb-0.0.5.dist-info/RECORD
