Metadata-Version: 2.1
Name: documentdb
Version: 0.0.5
Summary: 
Author: Dan Sikes
Author-email: dan@apagea.com
Requires-Python: >=3.9,<4.0
Classifier: Programming Language :: Python :: 3
Classifier: Programming Language :: Python :: 3.9
Classifier: Programming Language :: Python :: 3.10
Classifier: Programming Language :: Python :: 3.11
Classifier: Programming Language :: Python :: 3.12
Requires-Dist: databases[aiosqlite] (>=0.9.0,<0.10.0)
Requires-Dist: ujson (>=5.10.0,<6.0.0)
